rentalroi/__init__.py
rentalroi/rental.py
rentalroi-0.1.1.dist-info/METADATA
rentalroi-0.1.1.dist-info/WHEEL
rentalroi-0.1.1.dist-info/licenses/LICENSE
rentalroi-0.1.1.dist-info/RECORD
