Metadata-Version: 2.1
Name: RentalROI
Version: 0.1.1
Summary: A package to estimate ROI of rental properties
Project-URL: Homepage, https://github.com/DeadEntropy/RentalROI
Author: DeadEntropy
License: MIT License
Classifier: License :: OSI Approved :: MIT License
Classifier: Operating System :: OS Independent
Classifier: Programming Language :: Python :: 3
Requires-Python: >=3.7
